[
  {
    "date": "2025-09-01T13:00:00+02:00",
    "user_id": "jack",
    "source": "cointracking_api",
    "total_value_usd": 420125.36,
    "asset_count": 191,
    "group_count": 6,
    "diversity_score": 5,
    "top_holding_symbol": "BTC",
    "top_holding_percentage": 0.4,
    "group_distribution": {
      "BTC": 168050.144,
      "ETH": 92427.5792,
      "L1/L0 majors": 37811.2824,
      "Others": 79823.8184,
      "Stablecoins": 21006.268,
      "SOL": 4201.2536
    },
    "valuation_currency": "USD",
    "price_source": "cointracking_api",
    "pricing_timestamp": "2025-09-01T13:00:00+02:00"
  },
  {
    "date": "2025-09-02T13:00:00+02:00",
    "user_id": "jack",
    "source": "cointracking_api",
    "total_value_usd": 420192.82,
    "asset_count": 191,
    "group_count": 6,
    "diversity_score": 5,
    "top_holding_symbol": "BTC",
    "top_holding_percentage": 0.4,
    "group_distribution": {
      "BTC": 168077.12800000003,
      "ETH": 92442.4204,
      "L1/L0 majors": 37817.3538,
      "Others": 79836.6358,
      "Stablecoins": 21009.641000000003,
      "SOL": 4201.9282
    },
    "valuation_currency": "USD",
    "price_source": "cointracking_api",
    "pricing_timestamp": "2025-09-02T13:00:00+02:00"
  },
  {
    "date": "2025-09-03T13:00:00+02:00",
    "user_id": "jack",
    "source": "cointracking_api",
    "total_value_usd": 414429.71,
    "asset_count": 191,
    "group_count": 6,
    "diversity_score": 5,
    "top_holding_symbol": "BTC",
    "top_holding_percentage": 0.4,
    "group_distribution": {
      "BTC": 165771.88400000002,
      "ETH": 91174.5362,
      "L1/L0 majors": 37298.6739,
      "Others": 78741.6449,
      "Stablecoins": 20721.485500000003,
      "SOL": 4144.297100000001
    },
    "valuation_currency": "USD",
    "price_source": "cointracking_api",
    "pricing_timestamp": "2025-09-03T13:00:00+02:00"
  },
  {
    "date": "2025-09-04T13:00:00+02:00",
    "user_id": "jack",
    "source": "cointracking_api",
    "total_value_usd": 426599.53,
    "asset_count": 191,
    "group_count": 6,
    "diversity_score": 5,
    "top_holding_symbol": "BTC",
    "top_holding_percentage": 0.4,
    "group_distribution": {
      "BTC": 170639.81200000003,
      "ETH": 93851.89660000001,
      "L1/L0 majors": 38393.9577,
      "Others": 81053.91070000001,
      "Stablecoins": 21329.976500000004,
      "SOL": 4265.9953000000005
    },
    "valuation_currency": "USD",
    "price_source": "cointracking_api",
    "pricing_timestamp": "2025-09-04T13:00:00+02:00"
  },
  {
    "date": "2025-09-05T13:00:00+02:00",
    "user_id": "jack",
    "source": "cointracking_api",
    "total_value_usd": 416350.48,
    "asset_count": 191,
    "group_count": 6,
    "diversity_score": 5,
    "top_holding_symbol": "BTC",
    "top_holding_percentage": 0.4,
    "group_distribution": {
      "BTC": 166540.192,
      "ETH": 91597.1056,
      "L1/L0 majors": 37471.5432,
      "Others": 79106.5912,
      "Stablecoins": 20817.524,
      "SOL": 4163.5048
    },
    "valuation_currency": "USD",
    "price_source": "cointracking_api",
    "pricing_timestamp": "2025-09-05T13:00:00+02:00"
  },
  {
    "date": "2025-09-06T13:00:00+02:00",
    "user_id": "jack",
    "source": "cointracking_api",
    "total_value_usd": 419213.95,
    "asset_count": 191,
    "group_count": 6,
    "diversity_score": 5,
    "top_holding_symbol": "BTC",
    "top_holding_percentage": 0.4,
    "group_distribution": {
      "BTC": 167685.58000000002,
      "ETH": 92227.069,
      "L1/L0 majors": 37729.2555,
      "Others": 79650.6505,
      "Stablecoins": 20960.697500000002,
      "SOL": 4192.1395
    },
    "valuation_currency": "USD",
    "price_source": "cointracking_api",
    "pricing_timestamp": "2025-09-06T13:00:00+02:00"
  },
  {
    "date": "2025-09-07T13:00:00+02:00",
    "user_id": "jack",
    "source": "cointracking_api",
    "total_value_usd": 415421.45,
    "asset_count": 191,
    "group_count": 6,
    "diversity_score": 5,
    "top_holding_symbol": "BTC",
    "top_holding_percentage": 0.4,
    "group_distribution": {
      "BTC": 166168.58000000002,
      "ETH": 91392.719,
      "L1/L0 majors": 37387.9305,
      "Others": 78930.0755,
      "Stablecoins": 20771.072500000002,
      "SOL": 4154.2145
    },
    "valuation_currency": "USD",
    "price_source": "cointracking_api",
    "pricing_timestamp": "2025-09-07T13:00:00+02:00"
  },
  {
    "date": "2025-09-08T13:00:00+02:00",
    "user_id": "jack",
    "source": "cointracking_api",
    "total_value_usd": 419303.44,
    "asset_count": 191,
    "group_count": 6,
    "diversity_score": 5,
    "top_holding_symbol": "BTC",
    "top_holding_percentage": 0.4,
    "group_distribution": {
      "BTC": 167721.37600000002,
      "ETH": 92246.7568,
      "L1/L0 majors": 37737.3096,
      "Others": 79667.6536,
      "Stablecoins": 20965.172000000002,
      "SOL": 4193.0344000000005
    },
    "valuation_currency": "USD",
    "price_source": "cointracking_api",
    "pricing_timestamp": "2025-09-08T13:00:00+02:00"
  },
  {
    "date": "2025-09-09T13:00:00+02:00",
    "user_id": "jack",
    "source": "cointracking_api",
    "total_value_usd": 423597.71,
    "asset_count": 191,
    "group_count": 6,
    "diversity_score": 5,
    "top_holding_symbol": "BTC",
    "top_holding_percentage": 0.4,
    "group_distribution": {
      "BTC": 169439.08400000003,
      "ETH": 93191.49620000001,
      "L1/L0 majors": 38123.7939,
      "Others": 80483.56490000001,
      "Stablecoins": 21179.885500000004,
      "SOL": 4235.9771
    },
    "valuation_currency": "USD",
    "price_source": "cointracking_api",
    "pricing_timestamp": "2025-09-09T13:00:00+02:00"
  },
  {
    "date": "2025-09-10T13:00:00+02:00",
    "user_id": "jack",
    "source": "cointracking_api",
    "total_value_usd": 423258.64,
    "asset_count": 191,
    "group_count": 6,
    "diversity_score": 5,
    "top_holding_symbol": "BTC",
    "top_holding_percentage": 0.4,
    "group_distribution": {
      "BTC": 169303.456,
      "ETH": 93116.9008,
      "L1/L0 majors": 38093.2776,
      "Others": 80419.1416,
      "Stablecoins": 21162.932,
      "SOL": 4232.5864
    },
    "valuation_currency": "USD",
    "price_source": "cointracking_api",
    "pricing_timestamp": "2025-09-10T13:00:00+02:00"
  },
  {
    "date": "2025-09-11T13:00:00+02:00",
    "user_id": "jack",
    "source": "cointracking_api",
    "total_value_usd": 429235.23,
    "asset_count": 191,
    "group_count": 6,
    "diversity_score": 5,
    "top_holding_symbol": "BTC",
    "top_holding_percentage": 0.4,
    "group_distribution": {
      "BTC": 171694.092,
      "ETH": 94431.7506,
      "L1/L0 majors": 38631.170699999995,
      "Others": 81554.6937,
      "Stablecoins": 21461.7615,
      "SOL": 4292.3523
    },
    "valuation_currency": "USD",
    "price_source": "cointracking_api",
    "pricing_timestamp": "2025-09-11T13:00:00+02:00"
  },
  {
    "date": "2025-09-12T13:00:00+02:00",
    "user_id": "jack",
    "source": "cointracking_api",
    "total_value_usd": 433607.72,
    "asset_count": 191,
    "group_count": 6,
    "diversity_score": 5,
    "top_holding_symbol": "BTC",
    "top_holding_percentage": 0.4,
    "group_distribution": {
      "BTC": 173443.088,
      "ETH": 95393.6984,
      "L1/L0 majors": 39024.6948,
      "Others": 82385.4668,
      "Stablecoins": 21680.386,
      "SOL": 4336.0772
    },
    "valuation_currency": "USD",
    "price_source": "cointracking_api",
    "pricing_timestamp": "2025-09-12T13:00:00+02:00"
  },
  {
    "date": "2025-09-13T13:00:00+02:00",
    "user_id": "jack",
    "source": "cointracking_api",
    "total_value_usd": 445574.66,
    "asset_count": 191,
    "group_count": 6,
    "diversity_score": 5,
    "top_holding_symbol": "BTC",
    "top_holding_percentage": 0.4,
    "group_distribution": {
      "BTC": 178229.864,
      "ETH": 98026.4252,
      "L1/L0 majors": 40101.719399999994,
      "Others": 84659.1854,
      "Stablecoins": 22278.733,
      "SOL": 4455.7465999999995
    },
    "valuation_currency": "USD",
    "price_source": "cointracking_api",
    "pricing_timestamp": "2025-09-13T13:00:00+02:00"
  },
  {
    "date": "2025-09-14T13:00:00+02:00",
    "user_id": "jack",
    "source": "cointracking_api",
    "total_value_usd": 448392.88,
    "asset_count": 191,
    "group_count": 6,
    "diversity_score": 5,
    "top_holding_symbol": "BTC",
    "top_holding_percentage": 0.4,
    "group_distribution": {
      "BTC": 179357.152,
      "ETH": 98646.4336,
      "L1/L0 majors": 40355.3592,
      "Others": 85194.6472,
      "Stablecoins": 22419.644,
      "SOL": 4483.928800000001
    },
    "valuation_currency": "USD",
    "price_source": "cointracking_api",
    "pricing_timestamp": "2025-09-14T13:00:00+02:00"
  },
  {
    "date": "2025-09-15T13:00:00+02:00",
    "user_id": "jack",
    "source": "cointracking_api",
    "total_value_usd": 445452.26,
    "asset_count": 191,
    "group_count": 6,
    "diversity_score": 5,
    "top_holding_symbol": "BTC",
    "top_holding_percentage": 0.4,
    "group_distribution": {
      "BTC": 178180.904,
      "ETH": 97999.4972,
      "L1/L0 majors": 40090.7034,
      "Others": 84635.92940000001,
      "Stablecoins": 22272.613,
      "SOL": 4454.5226
    },
    "valuation_currency": "USD",
    "price_source": "cointracking_api",
    "pricing_timestamp": "2025-09-15T13:00:00+02:00"
  },
  {
    "date": "2025-09-16T13:00:00+02:00",
    "user_id": "jack",
    "source": "cointracking_api",
    "total_value_usd": 438847.74,
    "asset_count": 191,
    "group_count": 6,
    "diversity_score": 5,
    "top_holding_symbol": "BTC",
    "top_holding_percentage": 0.4,
    "group_distribution": {
      "BTC": 175539.09600000002,
      "ETH": 96546.5028,
      "L1/L0 majors": 39496.296599999994,
      "Others": 83381.0706,
      "Stablecoins": 21942.387000000002,
      "SOL": 4388.4774
    },
    "valuation_currency": "USD",
    "price_source": "cointracking_api",
    "pricing_timestamp": "2025-09-16T13:00:00+02:00"
  },
  {
    "date": "2025-09-17T13:00:00+02:00",
    "user_id": "jack",
    "source": "cointracking_api",
    "total_value_usd": 442753.65,
    "asset_count": 191,
    "group_count": 6,
    "diversity_score": 5,
    "top_holding_symbol": "BTC",
    "top_holding_percentage": 0.4,
    "group_distribution": {
      "BTC": 177101.46000000002,
      "ETH": 97405.803,
      "L1/L0 majors": 39847.8285,
      "Others": 84123.19350000001,
      "Stablecoins": 22137.682500000003,
      "SOL": 4427.5365
    },
    "valuation_currency": "USD",
    "price_source": "cointracking_api",
    "pricing_timestamp": "2025-09-17T13:00:00+02:00"
  },
  {
    "date": "2025-09-18T13:00:00+02:00",
    "user_id": "jack",
    "source": "cointracking_api",
    "total_value_usd": 440822.62,
    "asset_count": 191,
    "group_count": 6,
    "diversity_score": 5,
    "top_holding_symbol": "BTC",
    "top_holding_percentage": 0.4,
    "group_distribution": {
      "BTC": 176329.048,
      "ETH": 96980.9764,
      "L1/L0 majors": 39674.0358,
      "Others": 83756.2978,
      "Stablecoins": 22041.131,
      "SOL": 4408.2262
    },
    "valuation_currency": "USD",
    "price_source": "cointracking_api",
    "pricing_timestamp": "2025-09-18T13:00:00+02:00"
  },
  {
    "date": "2025-09-19T13:00:00+02:00",
    "user_id": "jack",
    "source": "cointracking_api",
    "total_value_usd": 451001.68,
    "asset_count": 191,
    "group_count": 6,
    "diversity_score": 5,
    "top_holding_symbol": "BTC",
    "top_holding_percentage": 0.4,
    "group_distribution": {
      "BTC": 180400.67200000002,
      "ETH": 99220.3696,
      "L1/L0 majors": 40590.1512,
      "Others": 85690.3192,
      "Stablecoins": 22550.084000000003,
      "SOL": 4510.0168
    },
    "valuation_currency": "USD",
    "price_source": "cointracking_api",
    "pricing_timestamp": "2025-09-19T13:00:00+02:00"
  },
  {
    "date": "2025-09-20T13:00:00+02:00",
    "user_id": "jack",
    "source": "cointracking_api",
    "total_value_usd": 440245.02,
    "asset_count": 191,
    "group_count": 6,
    "diversity_score": 5,
    "top_holding_symbol": "BTC",
    "top_holding_percentage": 0.4,
    "group_distribution": {
      "BTC": 176098.00800000003,
      "ETH": 96853.9044,
      "L1/L0 majors": 39622.0518,
      "Others": 83646.55380000001,
      "Stablecoins": 22012.251000000004,
      "SOL": 4402.4502
    },
    "valuation_currency": "USD",
    "price_source": "cointracking_api",
    "pricing_timestamp": "2025-09-20T13:00:00+02:00"
  },
  {
    "date": "2025-09-21T13:00:00+02:00",
    "user_id": "jack",
    "source": "cointracking_api",
    "total_value_usd": 442748.85,
    "asset_count": 191,
    "group_count": 6,
    "diversity_score": 5,
    "top_holding_symbol": "BTC",
    "top_holding_percentage": 0.4,
    "group_distribution": {
      "BTC": 177099.54,
      "ETH": 97404.74699999999,
      "L1/L0 majors": 39847.396499999995,
      "Others": 84122.2815,
      "Stablecoins": 22137.4425,
      "SOL": 4427.4884999999995
    },
    "valuation_currency": "USD",
    "price_source": "cointracking_api",
    "pricing_timestamp": "2025-09-21T13:00:00+02:00"
  },
  {
    "date": "2025-09-22T13:00:00+02:00",
    "user_id": "jack",
    "source": "cointracking_api",
    "total_value_usd": 446458.49,
    "asset_count": 191,
    "group_count": 6,
    "diversity_score": 5,
    "top_holding_symbol": "BTC",
    "top_holding_percentage": 0.4,
    "group_distribution": {
      "BTC": 178583.396,
      "ETH": 98220.86779999999,
      "L1/L0 majors": 40181.2641,
      "Others": 84827.1131,
      "Stablecoins": 22322.9245,
      "SOL": 4464.5849
    },
    "valuation_currency": "USD",
    "price_source": "cointracking_api",
    "pricing_timestamp": "2025-09-22T13:00:00+02:00"
  },
  {
    "date": "2025-09-23T13:00:00+02:00",
    "user_id": "jack",
    "source": "cointracking_api",
    "total_value_usd": 426404.64,
    "asset_count": 191,
    "group_count": 6,
    "diversity_score": 5,
    "top_holding_symbol": "BTC",
    "top_holding_percentage": 0.4,
    "group_distribution": {
      "BTC": 170561.85600000003,
      "ETH": 93809.0208,
      "L1/L0 majors": 38376.4176,
      "Others": 81016.88160000001,
      "Stablecoins": 21320.232000000004,
      "SOL": 4264.0464
    },
    "valuation_currency": "USD",
    "price_source": "cointracking_api",
    "pricing_timestamp": "2025-09-23T13:00:00+02:00"
  },
  {
    "date": "2025-09-24T13:00:00+02:00",
    "user_id": "jack",
    "source": "cointracking_api",
    "total_value_usd": 425008.82,
    "asset_count": 191,
    "group_count": 6,
    "diversity_score": 5,
    "top_holding_symbol": "BTC",
    "top_holding_percentage": 0.4,
    "group_distribution": {
      "BTC": 170003.52800000002,
      "ETH": 93501.9404,
      "L1/L0 majors": 38250.7938,
      "Others": 80751.6758,
      "Stablecoins": 21250.441000000003,
      "SOL": 4250.0882
    },
    "valuation_currency": "USD",
    "price_source": "cointracking_api",
    "pricing_timestamp": "2025-09-24T13:00:00+02:00"
  },
  {
    "date": "2025-09-25T13:00:00+02:00",
    "user_id": "jack",
    "source": "cointracking_api",
    "total_value_usd": 429577.15,
    "asset_count": 191,
    "group_count": 6,
    "diversity_score": 5,
    "top_holding_symbol": "BTC",
    "top_holding_percentage": 0.4,
    "group_distribution": {
      "BTC": 171830.86000000002,
      "ETH": 94506.97300000001,
      "L1/L0 majors": 38661.9435,
      "Others": 81619.6585,
      "Stablecoins": 21478.857500000002,
      "SOL": 4295.771500000001
    },
    "valuation_currency": "USD",
    "price_source": "cointracking_api",
    "pricing_timestamp": "2025-09-25T13:00:00+02:00"
  },
  {
    "date": "2025-09-26T13:00:00+02:00",
    "user_id": "jack",
    "source": "cointracking_api",
    "total_value_usd": 409210.39,
    "asset_count": 191,
    "group_count": 6,
    "diversity_score": 5,
    "top_holding_symbol": "BTC",
    "top_holding_percentage": 0.4,
    "group_distribution": {
      "BTC": 163684.15600000002,
      "ETH": 90026.2858,
      "L1/L0 majors": 36828.9351,
      "Others": 77749.9741,
      "Stablecoins": 20460.519500000002,
      "SOL": 4092.1039
    },
    "valuation_currency": "USD",
    "price_source": "cointracking_api",
    "pricing_timestamp": "2025-09-26T13:00:00+02:00"
  },
  {
    "date": "2025-09-27T13:00:00+02:00",
    "user_id": "jack",
    "source": "cointracking_api",
    "total_value_usd": 413601.89,
    "asset_count": 191,
    "group_count": 6,
    "diversity_score": 5,
    "top_holding_symbol": "BTC",
    "top_holding_percentage": 0.4,
    "group_distribution": {
      "BTC": 165440.75600000002,
      "ETH": 90992.4158,
      "L1/L0 majors": 37224.1701,
      "Others": 78584.3591,
      "Stablecoins": 20680.094500000003,
      "SOL": 4136.0189
    },
    "valuation_currency": "USD",
    "price_source": "cointracking_api",
    "pricing_timestamp": "2025-09-27T13:00:00+02:00"
  },
  {
    "date": "2025-09-28T13:00:00+02:00",
    "user_id": "jack",
    "source": "cointracking_api",
    "total_value_usd": 413682.15,
    "asset_count": 191,
    "group_count": 6,
    "diversity_score": 5,
    "top_holding_symbol": "BTC",
    "top_holding_percentage": 0.4,
    "group_distribution": {
      "BTC": 165472.86000000002,
      "ETH": 91010.073,
      "L1/L0 majors": 37231.3935,
      "Others": 78599.6085,
      "Stablecoins": 20684.107500000002,
      "SOL": 4136.8215
    },
    "valuation_currency": "USD",
    "price_source": "cointracking_api",
    "pricing_timestamp": "2025-09-28T13:00:00+02:00"
  },
  {
    "date": "2025-09-29T13:00:00+02:00",
    "user_id": "jack",
    "source": "cointracking_api",
    "total_value_usd": 413511.94,
    "asset_count": 191,
    "group_count": 6,
    "diversity_score": 5,
    "top_holding_symbol": "BTC",
    "top_holding_percentage": 0.4,
    "group_distribution": {
      "BTC": 165404.776,
      "ETH": 90972.6268,
      "L1/L0 majors": 37216.0746,
      "Others": 78567.2686,
      "Stablecoins": 20675.597,
      "SOL": 4135.1194000000005
    },
    "valuation_currency": "USD",
    "price_source": "cointracking_api",
    "pricing_timestamp": "2025-09-29T13:00:00+02:00"
  },
  {
    "date": "2025-09-30T13:00:00+02:00",
    "user_id": "jack",
    "source": "cointracking_api",
    "total_value_usd": 425922.04,
    "asset_count": 191,
    "group_count": 6,
    "diversity_score": 5,
    "top_holding_symbol": "BTC",
    "top_holding_percentage": 0.4,
    "group_distribution": {
      "BTC": 170368.816,
      "ETH": 93702.84879999999,
      "L1/L0 majors": 38332.9836,
      "Others": 80925.18759999999,
      "Stablecoins": 21296.102,
      "SOL": 4259.2204
    },
    "valuation_currency": "USD",
    "price_source": "cointracking_api",
    "pricing_timestamp": "2025-09-30T13:00:00+02:00"
  },
  {
    "date": "2025-10-01T13:00:00+02:00",
    "user_id": "jack",
    "source": "cointracking_api",
    "total_value_usd": 424603.19,
    "asset_count": 191,
    "group_count": 6,
    "diversity_score": 5,
    "top_holding_symbol": "BTC",
    "top_holding_percentage": 0.4,
    "group_distribution": {
      "BTC": 169841.276,
      "ETH": 93412.7018,
      "L1/L0 majors": 38214.2871,
      "Others": 80674.6061,
      "Stablecoins": 21230.1595,
      "SOL": 4246.0319
    },
    "valuation_currency": "USD",
    "price_source": "cointracking_api",
    "pricing_timestamp": "2025-10-01T13:00:00+02:00"
  },
  {
    "date": "2025-10-02T23:59:36.509251+02:00",
    "user_id": "jack",
    "source": "cointracking_api",
    "total_value_usd": 0,
    "asset_count": 0,
    "group_count": 0,
    "diversity_score": 0,
    "top_holding_symbol": "N/A",
    "top_holding_percentage": 0,
    "group_distribution": {},
    "valuation_currency": "USD",
    "price_source": "cointracking_api",
    "pricing_timestamp": "2025-10-02T23:59:36.509251+02:00"
  },
  {
    "date": "2025-10-03T23:59:17.765177+02:00",
    "user_id": "jack",
    "source": "cointracking_api",
    "total_value_usd": 460425.31355167,
    "asset_count": 193,
    "group_count": 6,
    "diversity_score": 5,
    "top_holding_symbol": "BTC",
    "top_holding_percentage": 0.39999544904049295,
    "group_distribution": {
      "Others": 86710.55176472003,
      "L1/L0 majors": 43313.595915959995,
      "BTC": 200081.46561886,
      "ETH": 104174.92781165,
      "Stablecoins": 23312.36804843,
      "SOL": 2832.40439205
    },
    "valuation_currency": "USD",
    "price_source": "cointracking_api",
    "pricing_timestamp": "2025-10-03T23:59:17.765177+02:00"
  },
  {
    "date": "2025-10-04T14:45:46.279404+02:00",
    "user_id": "jack",
    "source": "cointracking_api",
    "total_value_usd": 457759.70104892,
    "asset_count": 192,
    "group_count": 6,
    "diversity_score": 3,
    "top_holding_symbol": "BTC",
    "top_holding_percentage": 0.4023937502267918,
    "group_distribution": {
      "Others": 85339.94536380998,
      "L1/L0 majors": 42486.37812968999,
      "BTC": 200092.24285802,
      "ETH": 103625.15882193,
      "Stablecoins": 23414.304639809998,
      "SOL": 2801.67123566
    },
    "valuation_currency": "USD",
    "price_source": "cointracking_api",
    "pricing_timestamp": "2025-10-04T14:45:46.279404+02:00"
  },
  {
    "date": "2025-10-06T14:30:19.985508+02:00",
    "user_id": "jack",
    "source": "cointracking_api",
    "total_value_usd": 466957.34427924,
    "asset_count": 192,
    "group_count": 6,
    "diversity_score": 3,
    "top_holding_symbol": "BTC",
    "top_holding_percentage": 0.4026339331544778,
    "group_distribution": {
      "Others": 87457.40136859994,
      "L1/L0 majors": 43548.46320879001,
      "BTC": 204038.59557461,
      "ETH": 105655.70206693001,
      "Stablecoins": 23392.57234328,
      "SOL": 2864.60971703
    },
    "valuation_currency": "USD",
    "price_source": "cointracking_api",
    "pricing_timestamp": "2025-10-06T14:30:19.985508+02:00"
  },
  {
    "date": "2025-10-08T23:59:04.929466+02:00",
    "user_id": "jack",
    "source": "cointracking_api",
    "total_value_usd": 463449.54893163,
    "asset_count": 192,
    "group_count": 6,
    "diversity_score": 3,
    "top_holding_symbol": "BTC",
    "top_holding_percentage": 0.40028992653102746,
    "group_distribution": {
      "Others": 86217.31554827008,
      "L1/L0 majors": 43506.881946199996,
      "BTC": 201581.09714308998,
      "ETH": 103980.55126177,
      "Stablecoins": 25373.24620906,
      "SOL": 2790.45682324
    },
    "valuation_currency": "USD",
    "price_source": "cointracking_api",
    "pricing_timestamp": "2025-10-08T23:59:04.929466+02:00"
  },
  {
    "date": "2025-10-09T10:45:26.908141+02:00",
    "user_id": "jack",
    "source": "cointracking_api",
    "total_value_usd": 453980.83354874,
    "asset_count": 192,
    "group_count": 6,
    "diversity_score": 3,
    "top_holding_symbol": "BTC",
    "top_holding_percentage": 0.40236936394604095,
    "group_distribution": {
      "Others": 83461.21623783,
      "L1/L0 majors": 42593.84039551,
      "BTC": 198470.61022590002,
      "ETH": 101394.68432416,
      "Stablecoins": 25352.587959110002,
      "SOL": 2707.89440623
    },
    "valuation_currency": "USD",
    "price_source": "cointracking_api",
    "pricing_timestamp": "2025-10-09T10:45:26.908141+02:00"
  },
  {
    "date": "2025-09-30T13:42:28.722088",
    "user_id": "jack",
    "source": "cointracking",
    "total_value_usd": 133100.0,
    "asset_count": 5,
    "group_count": 3,
    "diversity_score": 1,
    "top_holding_symbol": "ETH",
    "top_holding_percentage": 0.5634861006761833,
    "group_distribution": {
      "BTC": 33600.0,
      "ETH": 75000.0,
      "Others": 24500.0
    }
  }
]